bsutils/__init__.py
bsutils/exception.py
bsutils/file.py
bsutils/io.py
bsutils/iterator.py
bsutils/json.py
bsutils/option.py
bsutils/py.typed
bsutils/random.py
bsutils/result.py
bsutils/version.py
bsutils-0.0.5.dist-info/METADATA
bsutils-0.0.5.dist-info/WHEEL
bsutils-0.0.5.dist-info/licenses/LICENSE
bsutils-0.0.5.dist-info/RECORD
