Metadata-Version: 2.4
Name: bsutils
Version: 0.0.5
Summary: A collection of basic python utilities.
Project-URL: Homepage, https://github.com/wangzhen0518/bsutils
Project-URL: Issues, https://github.com/wangzhen0518/bsutils/issues
Author-email: wangzhen0518 <wangzhen0518@126.com>
License-File: LICENSE
Classifier: Operating System :: OS Independent
Classifier: Programming Language :: Python :: 3
Requires-Python: >=3.6
Requires-Dist: pyjson5
